MANIFEST.in
README.md
setup.py
router_engine/__init__.py
router_engine/router.py
router_engine/rule_evaluator.py
router_engine/rule_executor.py
router_engine/rules_parser.py
router_engine/rules_updater.py
router_engine/schema.json
router_engine/simulation_server.py
router_engine/helpers/__init__.py
router_engine/helpers/classes.py
routing_engine.egg-info/PKG-INFO
routing_engine.egg-info/SOURCES.txt
routing_engine.egg-info/dependency_links.txt
routing_engine.egg-info/requires.txt
routing_engine.egg-info/top_level.txt