Metadata-Version: 2.1
Name: routing-engine
Version: 0.1.11
Summary: A routing engine for Python
Home-page: https://gitlab.internal.ate.lc/numbers-lookup/routing-engine
Author: Annecto
Author-email: info@annecto.com
License: UNKNOWN
Platform: UNKNOWN
